tipo_cambio/__init__.py
tipo_cambio/cambio_scrap.py
tipo_cambio/exceptions.py
FactoringTotal-1.0.2.dist-info/METADATA
FactoringTotal-1.0.2.dist-info/WHEEL
FactoringTotal-1.0.2.dist-info/top_level.txt
FactoringTotal-1.0.2.dist-info/RECORD
